AUTHORS
CHANGELOG
LICENSE
MANIFEST.in
README.markdown
setup.py
pybloomfiltermmap.egg-info/PKG-INFO
pybloomfiltermmap.egg-info/SOURCES.txt
pybloomfiltermmap.egg-info/dependency_links.txt
pybloomfiltermmap.egg-info/top_level.txt
src/Makefile
src/MurmurHash3.c
src/MurmurHash3.h
src/bloomfilter.c
src/bloomfilter.h
src/cbloomfilter.pxd
src/md5.c
src/md5.h
src/mmapbitarray.c
src/mmapbitarray.h
src/primetester.c
src/primetester.h
src/pybloomfilter.c
src/pybloomfilter.pyx
src/superfast.h
tests/__init__.py
tests/accuracytest.py
tests/simpletest.py
tests/comparisons/accuracytest.py
tests/comparisons/speedtest.py
tests/comparisons/testwords
tests/comparisons/words