Metadata-Version: 1.1
Name: pybloomfiltermmap
Version: 0.3.15
Summary: A Bloom filter (bloomfilter) for Python built on mmap
Home-page: http://github.com/axiak/pybloomfiltermmap/
Author: Michael Axiak, Rob Stacey
Author-email: mike@axiak.net
License: MIT License
Platform: UNKNOWN
Classifier: Intended Audience :: Developers
Classifier: License :: OSI Approved :: MIT License
Classifier: Programming Language :: C
Classifier: Programming Language :: Cython
Classifier: Programming Language :: Python
Classifier: Topic :: Software Development :: Libraries :: Python Modules
